odoo9_addon_account_move_transactionid_import-9.0.1.0.0.99.dev20-py2.7-nspkg.pth
odoo9_addon_account_move_transactionid_import-9.0.1.0.0.99.dev20.dist-info/DESCRIPTION.rst
odoo9_addon_account_move_transactionid_import-9.0.1.0.0.99.dev20.dist-info/METADATA
odoo9_addon_account_move_transactionid_import-9.0.1.0.0.99.dev20.dist-info/RECORD
odoo9_addon_account_move_transactionid_import-9.0.1.0.0.99.dev20.dist-info/WHEEL
odoo9_addon_account_move_transactionid_import-9.0.1.0.0.99.dev20.dist-info/metadata.json
odoo9_addon_account_move_transactionid_import-9.0.1.0.0.99.dev20.dist-info/namespace_packages.txt
odoo9_addon_account_move_transactionid_import-9.0.1.0.0.99.dev20.dist-info/top_level.txt
odoo_addons/account_move_transactionid_import/README.rst
odoo_addons/account_move_transactionid_import/__init__.py
odoo_addons/account_move_transactionid_import/__openerp__.py
odoo_addons/account_move_transactionid_import/data/completion_rule_data.xml
odoo_addons/account_move_transactionid_import/data/statement.csv
odoo_addons/account_move_transactionid_import/data/statement.xls
odoo_addons/account_move_transactionid_import/i18n/account_move_transactionid_import.pot
odoo_addons/account_move_transactionid_import/i18n/ar.po
odoo_addons/account_move_transactionid_import/i18n/bs.po
odoo_addons/account_move_transactionid_import/i18n/ca.po
odoo_addons/account_move_transactionid_import/i18n/ca_ES.po
odoo_addons/account_move_transactionid_import/i18n/cs.po
odoo_addons/account_move_transactionid_import/i18n/da.po
odoo_addons/account_move_transactionid_import/i18n/de.po
odoo_addons/account_move_transactionid_import/i18n/en_GB.po
odoo_addons/account_move_transactionid_import/i18n/es.po
odoo_addons/account_move_transactionid_import/i18n/es_CR.po
odoo_addons/account_move_transactionid_import/i18n/es_EC.po
odoo_addons/account_move_transactionid_import/i18n/es_ES.po
odoo_addons/account_move_transactionid_import/i18n/es_MX.po
odoo_addons/account_move_transactionid_import/i18n/es_VE.po
odoo_addons/account_move_transactionid_import/i18n/et.po
odoo_addons/account_move_transactionid_import/i18n/fi.po
odoo_addons/account_move_transactionid_import/i18n/fr.po
odoo_addons/account_move_transactionid_import/i18n/gl.po
odoo_addons/account_move_transactionid_import/i18n/hr.po
odoo_addons/account_move_transactionid_import/i18n/hr_HR.po
odoo_addons/account_move_transactionid_import/i18n/hu.po
odoo_addons/account_move_transactionid_import/i18n/id.po
odoo_addons/account_move_transactionid_import/i18n/it.po
odoo_addons/account_move_transactionid_import/i18n/ja.po
